[
  {"topic": "sarayu/d1/topic1|m/s"},
  {"topic": "sarayu/d1/topic2|m/s"},
  {"topic": "sarayu/d1/topic3|m/s"},
  {"topic": "sarayu/d1/topic4|m/s"},
  {"topic": "sarayu/d1/topic5|m/s"},
  {"topic": "sarayu/d1/topic6|m/s"},
  {"topic": "sarayu/d1/topic7|m/s"},
  {"topic": "sarayu/d1/topic8|m/s"},
  {"topic": "sarayu/d1/topic9|m/s"},
  {"topic": "sarayu/d1/topic10|m/s"},
  {"topic": "sarayu/d1/topic11|m/s"},
  {"topic": "sarayu/d1/topic12|m/s"},
  {"topic": "sarayu/d1/topic13|m/s"},
  {"topic": "sarayu/d1/topic14|m/s"},
  {"topic": "sarayu/d1/topic15|m/s"},
  {"topic": "sarayu/d1/topic16|m/s"},
  {"topic": "sarayu/d1/topic17|m/s"},
  {"topic": "sarayu/d1/topic18|m/s"},
  {"topic": "sarayu/d1/topic19|m/s"},
  {"topic": "sarayu/d1/topic20|m/s"},
  {"topic": "sarayu/d1/topic21|m/s"},
  {"topic": "sarayu/d1/topic22|m/s"},
  {"topic": "sarayu/d1/topic23|m/s"},
  {"topic": "sarayu/d1/topic24|m/s"},
  {"topic": "sarayu/d1/topic25|m/s"},
  {"topic": "sarayu/d1/topic26|m/s"},
  {"topic": "sarayu/d1/topic27|m/s"},
  {"topic": "sarayu/d1/topic28|m/s"},
  {"topic": "sarayu/d1/topic29|m/s"},
  {"topic": "sarayu/d1/topic30|m/s"},
  {"topic": "sarayu/d1/topic31|m/s"},
  {"topic": "sarayu/d1/topic32|m/s"},
  {"topic": "sarayu/d1/topic33|m/s"},
  {"topic": "sarayu/d1/topic34|m/s"},
  {"topic": "sarayu/d1/topic35|m/s"},
  {"topic": "sarayu/d1/topic36|m/s"},
  {"topic": "sarayu/d1/topic37|m/s"},
  {"topic": "sarayu/d1/topic38|m/s"},
  {"topic": "sarayu/d1/topic39|m/s"},
  {"topic": "sarayu/d1/topic40|m/s"},
  {"topic": "sarayu/d1/topic41|m/s"},
  {"topic": "sarayu/d1/topic42|m/s"},
  {"topic": "sarayu/d1/topic43|m/s"},
  {"topic": "sarayu/d1/topic44|m/s"},
  {"topic": "sarayu/d1/topic45|m/s"},
  {"topic": "sarayu/d1/topic46|m/s"},
  {"topic": "sarayu/d1/topic47|m/s"},
  {"topic": "sarayu/d1/topic48|m/s"},
  {"topic": "sarayu/d1/topic49|m/s"},
  {"topic": "sarayu/d1/topic50|m/s"},
  {"topic": "sarayu/d1/topic51|m/s"},
  {"topic": "sarayu/d1/topic52|m/s"},
  {"topic": "sarayu/d1/topic53|m/s"},
  {"topic": "sarayu/d1/topic54|m/s"},
  {"topic": "sarayu/d1/topic55|m/s"},
  {"topic": "sarayu/d1/topic56|m/s"},
  {"topic": "sarayu/d1/topic57|m/s"},
  {"topic": "sarayu/d1/topic58|m/s"},
  {"topic": "sarayu/d1/topic59|m/s"},
  {"topic": "sarayu/d1/topic60|m/s"},
  {"topic": "sarayu/d1/topic61|m/s"},
  {"topic": "sarayu/d1/topic62|m/s"},
  {"topic": "sarayu/d1/topic63|m/s"},
  {"topic": "sarayu/d1/topic64|m/s"},
  {"topic": "sarayu/d1/topic65|m/s"},
  {"topic": "sarayu/d1/topic66|m/s"},
  {"topic": "sarayu/d1/topic67|m/s"},
  {"topic": "sarayu/d1/topic68|m/s"},
  {"topic": "sarayu/d1/topic69|m/s"},
  {"topic": "sarayu/d1/topic70|m/s"},
  {"topic": "sarayu/d1/topic71|m/s"},
  {"topic": "sarayu/d1/topic72|m/s"},
  {"topic": "sarayu/d1/topic73|m/s"},
  {"topic": "sarayu/d1/topic74|m/s"},
  {"topic": "sarayu/d1/topic75|m/s"},
  {"topic": "sarayu/d1/topic76|m/s"},
  {"topic": "sarayu/d1/topic77|m/s"},
  {"topic": "sarayu/d1/topic78|m/s"},
  {"topic": "sarayu/d1/topic79|m/s"},
  {"topic": "sarayu/d1/topic80|m/s"},
  {"topic": "sarayu/d1/topic81|m/s"},
  {"topic": "sarayu/d1/topic82|m/s"},
  {"topic": "sarayu/d1/topic83|m/s"},
  {"topic": "sarayu/d1/topic84|m/s"},
  {"topic": "sarayu/d1/topic85|m/s"},
  {"topic": "sarayu/d1/topic86|m/s"},
  {"topic": "sarayu/d1/topic87|m/s"},
  {"topic": "sarayu/d1/topic88|m/s"},
  {"topic": "sarayu/d1/topic89|m/s"},
  {"topic": "sarayu/d1/topic90|m/s"},
  {"topic": "sarayu/d1/topic91|m/s"},
  {"topic": "sarayu/d1/topic92|m/s"},
  {"topic": "sarayu/d1/topic93|m/s"},
  {"topic": "sarayu/d1/topic94|m/s"},
  {"topic": "sarayu/d1/topic95|m/s"},
  {"topic": "sarayu/d1/topic96|m/s"},
  {"topic": "sarayu/d1/topic97|m/s"},
  {"topic": "sarayu/d1/topic98|m/s"},
  {"topic": "sarayu/d1/topic99|m/s"},
  {"topic": "sarayu/d1/topic100|m/s"}
]
